derate/__init__.py
derate/cli.py
derate/derate.py
derate-0.1.0.dist-info/AUTHORS.rst
derate-0.1.0.dist-info/LICENSE
derate-0.1.0.dist-info/METADATA
derate-0.1.0.dist-info/WHEEL
derate-0.1.0.dist-info/entry_points.txt
derate-0.1.0.dist-info/top_level.txt
derate-0.1.0.dist-info/RECORD
