Metadata-Version: 2.1
Name: derate
Version: 0.1.0
Summary: A machine wide rate limiter.
Home-page: https://github.com/jeandet/derate
Author: Alexis Jeandet
Author-email: alexis.jeandet@member.fsf.org
License: GNU General Public License v3
Keywords: derate
Platform: UNKNOWN
Classifier: Development Status :: 2 - Pre-Alpha
Classifier: Intended Audience :: Developers
Classifier: License :: OSI Approved :: GNU General Public License v3 (GPLv3)
Classifier: Natural Language :: English
Classifier: Programming Language :: Python :: 3
Classifier: Programming Language :: Python :: 3.6
Classifier: Programming Language :: Python :: 3.7
Classifier: Programming Language :: Python :: 3.8
Requires-Python: >=3.6
Requires-Dist: Click (>=7.0)
